pylint_web2py3/__init__.py
pylint_web2py3-0.9.0.dist-info/COPYING
pylint_web2py3-0.9.0.dist-info/METADATA
pylint_web2py3-0.9.0.dist-info/WHEEL
pylint_web2py3-0.9.0.dist-info/top_level.txt
pylint_web2py3-0.9.0.dist-info/RECORD
