Metadata-Version: 2.1
Name: pylint-web2py3
Version: 0.9.0
Summary: pylint_web2py3 is a disciple of pylint-web2py and pylint_web2py2 with better web2py support
Home-page: https://github.com/vinyldarkscratch/pylint_web2py3
Author: Vinyl Darkscratch
Author-email: vinyldarkscratch@gooborg.com
Maintainer: Vinyl Darkscratch
Maintainer-email: vinyldarkscratch@gooborg.com
License: http://www.gnu.org/copyleft/gpl.html
Keywords: pylint web2py plugin
Platform: any
Requires-Dist: astroid (>=1.3.0)
Requires-Dist: pylint (>=1.2.0)
